visier/__init__.py
visier/sdk/__init__.py
visier/sdk/api/__init__.py
visier/sdk/api/data_handling/__init__.py
visier/sdk/api/data_handling/api_client.py
visier/sdk/api/data_handling/api_response.py
visier/sdk/api/data_handling/configuration.py
visier/sdk/api/data_handling/exceptions.py
visier/sdk/api/data_handling/py.typed
visier/sdk/api/data_handling/rest.py
visier/sdk/api/data_handling/api/__init__.py
visier/sdk/api/data_handling/api/data_and_job_handling_api.py
visier/sdk/api/data_handling/models/__init__.py
visier/sdk/api/data_handling/models/adp_auth_params_dto.py
visier/sdk/api/data_handling/models/assign_connector_credential_request.py
visier/sdk/api/data_handling/models/assign_connector_credentials_by_tenant_response_dto.py
visier/sdk/api/data_handling/models/assign_connector_credentials_response_dto.py
visier/sdk/api/data_handling/models/assign_connector_with_credentials_response_dto.py
visier/sdk/api/data_handling/models/assigned_credential_info_response_dto.py
visier/sdk/api/data_handling/models/bamboo_auth_params_dto.py
visier/sdk/api/data_handling/models/basic_s3_auth_params_dto.py
visier/sdk/api/data_handling/models/big_query_auth_params_dto.py
visier/sdk/api/data_handling/models/big_query_service_account_params_dto.py
visier/sdk/api/data_handling/models/cancel_job_batch_from_job_id_dto.py
visier/sdk/api/data_handling/models/connector.py
visier/sdk/api/data_handling/models/connector_info_response_dto.py
visier/sdk/api/data_handling/models/copy_s3_auth_params_dto.py
visier/sdk/api/data_handling/models/credential_creation_api_response_dto.py
visier/sdk/api/data_handling/models/data_categories_response_dto.py
visier/sdk/api/data_handling/models/data_category_response_dto.py
visier/sdk/api/data_handling/models/data_load_request.py
visier/sdk/api/data_handling/models/data_load_request_model.py
visier/sdk/api/data_handling/models/data_load_response.py
visier/sdk/api/data_handling/models/data_provider_auth_information_dto.py
visier.sdk.api.data_handling-0.0.4.dist-info/METADATA
visier.sdk.api.data_handling-0.0.4.dist-info/WHEEL
visier.sdk.api.data_handling-0.0.4.dist-info/top_level.txt
visier.sdk.api.data_handling-0.0.4.dist-info/RECORD
